scifloat/__init__.py
scifloat/scifloat.py
scifloat/sciround.py
scifloat-2.1.0.dist-info/LICENSE
scifloat-2.1.0.dist-info/METADATA
scifloat-2.1.0.dist-info/WHEEL
scifloat-2.1.0.dist-info/top_level.txt
scifloat-2.1.0.dist-info/RECORD
